lsy_test/__init__.py
lsy_test/test.py
lsy_test-0.0.1.dist-info/METADATA
lsy_test-0.0.1.dist-info/WHEEL
lsy_test-0.0.1.dist-info/top_level.txt
lsy_test-0.0.1.dist-info/RECORD
