Metadata-Version: 2.1
Name: lsy-test
Version: 0.0.1
Summary: for explain about pypi deploy
Home-page: UNKNOWN
Author: lsy
Author-email: lsy0927@gaeasoft.co.kr
License: UNKNOWN
Keywords: pypi deploy
Platform: UNKNOWN
Classifier: Programming Language :: Python :: 3
Classifier: Programming Language :: Python :: 3.2
Classifier: Programming Language :: Python :: 3.3
Classifier: Programming Language :: Python :: 3.4
Classifier: Programming Language :: Python :: 3.5
Classifier: Programming Language :: Python :: 3.6
Classifier: Programming Language :: Python :: 3.7
Requires-Python: >=3
